biotuner/__init__.py
biotuner/biocolors.py
biotuner/bioelements.py
biotuner/biotuner2d.py
biotuner/biotuner_group.py
biotuner/biotuner_object.py
biotuner/biotuner_utils.py
biotuner/dictionaries.py
biotuner/harmonic_connectivity.py
biotuner/harmonic_spectrum.py
biotuner/metrics.py
biotuner/peaks_extension.py
biotuner/peaks_extraction.py
biotuner/plot_config.py
biotuner/plot_utils.py
biotuner/rhythm_construction.py
biotuner/scale_construction.py
biotuner/transitional_harmony.py
biotuner/vizs.py
biotuner-0.1.0.dist-info/licenses/LICENSE.txt
biotuner-0.1.0.dist-info/METADATA
biotuner-0.1.0.dist-info/WHEEL
biotuner-0.1.0.dist-info/top_level.txt
biotuner-0.1.0.dist-info/RECORD
