Metadata-Version: 2.4
Name: biotuner
Version: 0.1.0
Summary: Time series harmonic analysis for adaptive tuning systems and microtonal exploration
Author-email: Antoine Bellemare <antoine.bellemare9@gmail.com>
License: MIT
Project-URL: Homepage, https://github.com/antoinebellemare/biotuner
Keywords: biosignal,harmony,tuning,eeg,microtonality,music,time series
Classifier: Programming Language :: Python :: 3.7
Classifier: Programming Language :: Python :: 3.8
Classifier: Programming Language :: Python :: 3.9
Classifier: Programming Language :: Python :: 3.10
Classifier: Programming Language :: Python :: 3.11
Classifier: Operating System :: OS Independent
Classifier: License :: OSI Approved :: MIT License
Requires-Python: >=3.6
License-File: LICENSE.txt
Requires-Dist: matplotlib>=3.5.3
Requires-Dist: seaborn>=0.12.1
Requires-Dist: mne>=1.4.0
Requires-Dist: fooof>=1.0.0
Requires-Dist: emd>=0.5.5
Requires-Dist: contfrac>=1.0.0
Requires-Dist: scipy>=1.7.3
Requires-Dist: numpy<2.0,>=1.21.4
Requires-Dist: mido>=1.2.10
Requires-Dist: sympy>=1.12
Requires-Dist: pytest>=7.0.0
Provides-Extra: interactive
Requires-Dist: ipywidgets>=8.0.4; extra == "interactive"
Requires-Dist: pygame>=2.1.2; extra == "interactive"
Requires-Dist: pyACA>=0.3.1; extra == "interactive"
Requires-Dist: pactools>=0.3.1; extra == "interactive"
Requires-Dist: colorednoise>=2.1.0; extra == "interactive"
Requires-Dist: neurokit2>=0.2.2; extra == "interactive"
Requires-Dist: pingouin; extra == "interactive"
Requires-Dist: plotly>=5.13.1; extra == "interactive"
Requires-Dist: PyWavelets>=1.4.1; extra == "interactive"
Requires-Dist: neurodsp>=2.2; extra == "interactive"
Requires-Dist: IPython>=7.0.0; extra == "interactive"
Requires-Dist: scikit-learn; extra == "interactive"
Provides-Extra: gui
Requires-Dist: streamlit>=1.15.0; extra == "gui"
Requires-Dist: streamlit-echarts>=0.4.0; extra == "gui"
Requires-Dist: librosa>=0.9.2; extra == "gui"
Requires-Dist: sounddevice>=0.4.5; extra == "gui"
Requires-Dist: music21>=6.7.0; extra == "gui"
Requires-Dist: plotly>=5.0.0; extra == "gui"
Requires-Dist: pytuning; extra == "gui"
Dynamic: license-file
